{
  "userSays": [
    {
      "id": "6b0c1b70-7a00-485f-8c76-ff5da28a6c8d",
      "data": [
        {
          "text": "could you speak a little more softly"
        }
      ],
      "isTemplate": false,
      "count": 0
    },
    {
      "id": "0ceb0419-6d81-4cc7-88d4-3d274b1a865d",
      "data": [
        {
          "text": "turn it up"
        }
      ],
      "isTemplate": false,
      "count": 0
    },
    {
      "id": "189ec3d2-e057-4d77-99d8-3f0239a5fbfc",
      "data": [
        {
          "text": "just increase the volume a little"
        }
      ],
      "isTemplate": false,
      "count": 0
    },
    {
      "id": "271d6e1d-5639-43fa-8831-894540dcb45f",
      "data": [
        {
          "text": "olly turn the volume up"
        }
      ],
      "isTemplate": false,
      "count": 0
    },
    {
      "id": "388505e8-b487-41de-8843-fb66c954fd9b",
      "data": [
        {
          "text": "raise volume "
        },
        {
          "text": "to level seven",
          "alias": "change_amount",
          "meta": "@change_amount",
          "userDefined": true
        },
        {
          "text": " on "
        },
        {
          "text": "music player",
          "alias": "device_type",
          "meta": "@device_type",
          "userDefined": true
        }
      ],
      "isTemplate": false,
      "count": 0
    },
    {
      "id": "2ae97955-eda2-4850-bf4f-b8601dcaa783",
      "data": [
        {
          "text": "i want the speakers turned up high"
        }
      ],
      "isTemplate": false,
      "count": 0
    },
    {
      "id": "c569af3c-12d6-48c2-b678-5a2ab298a8e7",
      "data": [
        {
          "text": "rise volume"
        }
      ],
      "isTemplate": false,
      "count": 0
    },
    {
      "id": "ad8b719e-bc9b-471c-9113-0918e1ed7732",
      "data": [
        {
          "text": "please increase the volume of the music "
        },
        {
          "text": "hips don't lie",
          "alias": "song_name",
          "meta": "@song_name",
          "userDefined": true
        }
      ],
      "isTemplate": false,
      "count": 0
    },
    {
      "id": "5ff351b8-8db6-49d8-a650-0d928092c34d",
      "data": [
        {
          "text": "raise the volume of my "
        },
        {
          "text": "music player",
          "alias": "device_type",
          "meta": "@device_type",
          "userDefined": true
        },
        {
          "text": " "
        },
        {
          "text": "by fifty percent",
          "alias": "change_amount",
          "meta": "@change_amount",
          "userDefined": true
        }
      ],
      "isTemplate": false,
      "count": 0
    },
    {
      "id": "a730e544-58a0-4f5f-9a39-4bec9198e364",
      "data": [
        {
          "text": "speak as loud as you can"
        }
      ],
      "isTemplate": false,
      "count": 0
    },
    {
      "id": "aabc61be-99a9-4d6a-b3b9-b41a773c577e",
      "data": [
        {
          "text": "increase volume please"
        }
      ],
      "isTemplate": false,
      "count": 0
    },
    {
      "id": "feca43c6-185b-4903-b941-e0f5d4c52e6c",
      "data": [
        {
          "text": "make this a bit louder"
        }
      ],
      "isTemplate": false,
      "count": 0
    },
    {
      "id": "05822a9c-de4f-4df1-88a9-77260d1c8d94",
      "data": [
        {
          "text": "increase volume "
        },
        {
          "text": "to fifty percent",
          "alias": "change_amount",
          "meta": "@change_amount",
          "userDefined": true
        }
      ],
      "isTemplate": false,
      "count": 0
    },
    {
      "id": "0e5fdbd4-49e8-43a1-ac08-43968d9caeb2",
      "data": [
        {
          "text": "please raise the volume of speaker"
        }
      ],
      "isTemplate": false,
      "count": 0
    },
    {
      "id": "29f60a01-6153-4e32-81e2-21ddcc0e1b2c",
      "data": [
        {
          "text": "louder"
        }
      ],
      "isTemplate": false,
      "count": 0
    },
    {
      "id": "762001a8-f8bf-4ada-aec4-a3310f396711",
      "data": [
        {
          "text": "i cant hear a thing"
        }
      ],
      "isTemplate": false,
      "count": 0
    },
    {
      "id": "81909d73-d522-4945-998d-ab29a896b17e",
      "data": [
        {
          "text": "set the volume higher"
        }
      ],
      "isTemplate": false,
      "count": 0
    },
    {
      "id": "5fa3a9ab-9ff5-4c3a-9424-8717849e2eff",
      "data": [
        {
          "text": "i need you to have the volume louder"
        }
      ],
      "isTemplate": false,
      "count": 0
    },
    {
      "id": "64e44444-8061-47a1-9538-c192792d6785",
      "data": [
        {
          "text": "turn up the volume of my speakers"
        }
      ],
      "isTemplate": false,
      "count": 0
    },
    {
      "id": "b083ed1b-00b1-4e45-8f47-935bc1db17ba",
      "data": [
        {
          "text": "volume up"
        }
      ],
      "isTemplate": false,
      "count": 0
    },
    {
      "id": "20a10b42-be88-40c5-9a2e-e8d2c7f2e768",
      "data": [
        {
          "text": "please unmute the settings"
        }
      ],
      "isTemplate": false,
      "count": 0
    },
    {
      "id": "83d6d315-506f-4604-8cf4-c70c66d32b52",
      "data": [
        {
          "text": "audio up"
        }
      ],
      "isTemplate": false,
      "count": 0
    },
    {
      "id": "87c1bcc8-d4cc-473c-8f03-a3af933a508a",
      "data": [
        {
          "text": "the volume of the music playing now should be raised"
        }
      ],
      "isTemplate": false,
      "count": 0
    },
    {
      "id": "f6c6683c-b9a0-4e88-a517-c4250714e2f5",
      "data": [
        {
          "text": "raise the volume of the speakers"
        }
      ],
      "isTemplate": false,
      "count": 0
    },
    {
      "id": "b68799b6-acdb-471c-acc5-934a8db23f3c",
      "data": [
        {
          "text": "turn my audio higher"
        }
      ],
      "isTemplate": false,
      "count": 0
    },
    {
      "id": "73f1512c-4922-4e35-9947-9b5599702416",
      "data": [
        {
          "text": "can you increase the volume of the speakers"
        }
      ],
      "isTemplate": false,
      "count": 0
    },
    {
      "id": "227e6b81-a074-4af4-91ee-4934064586a4",
      "data": [
        {
          "text": "raise the volume "
        },
        {
          "text": "to fifty",
          "alias": "change_amount",
          "meta": "@change_amount",
          "userDefined": true
        }
      ],
      "isTemplate": false,
      "count": 0
    },
    {
      "id": "5722b508-fb88-46e2-bed7-a233ffc79afe",
      "data": [
        {
          "text": "Volume louder softer"
        }
      ],
      "isTemplate": false,
      "count": 0
    },
    {
      "id": "a192408d-6834-4f68-8ac9-b2aa0a281d2e",
      "data": [
        {
          "text": "turn up the sound"
        }
      ],
      "isTemplate": false,
      "count": 0
    },
    {
      "id": "af22ace0-c74f-4d24-af1a-051c09be8fe8",
      "data": [
        {
          "text": "i need to hear the volume of the current music"
        }
      ],
      "isTemplate": false,
      "count": 0
    },
    {
      "id": "34c634e6-835c-4871-86d0-0f301aac73ba",
      "data": [
        {
          "text": "please increase the volume"
        }
      ],
      "isTemplate": false,
      "count": 0
    },
    {
      "id": "efd3a323-c031-4a11-842f-3b69414830d0",
      "data": [
        {
          "text": "please turn the music up"
        }
      ],
      "isTemplate": false,
      "count": 0
    },
    {
      "id": "11e80a7c-18b6-4158-b7b3-024993700b4b",
      "data": [
        {
          "text": "could you please yell the answer out to me"
        }
      ],
      "isTemplate": false,
      "count": 0
    },
    {
      "id": "aece3c19-0aec-49e7-ad16-8352fa0ff54e",
      "data": [
        {
          "text": "please speak loud"
        }
      ],
      "isTemplate": false,
      "count": 0
    },
    {
      "id": "d635ed89-24eb-445d-a154-473692696477",
      "data": [
        {
          "text": "on the "
        },
        {
          "text": "music player",
          "alias": "device_type",
          "meta": "@device_type",
          "userDefined": true
        },
        {
          "text": " set the volume level at "
        },
        {
          "text": "sixty",
          "alias": "change_amount",
          "meta": "@change_amount",
          "userDefined": true
        }
      ],
      "isTemplate": false,
      "count": 0
    },
    {
      "id": "f8d6bab0-2a29-4b16-9808-26a7cf831dad",
      "data": [
        {
          "text": "raise speaker volume"
        }
      ],
      "isTemplate": false,
      "count": 0
    },
    {
      "id": "c7dfcc36-b8ed-49a8-8fdb-8ac8a32ddc16",
      "data": [
        {
          "text": "raise the volume of the current music"
        }
      ],
      "isTemplate": false,
      "count": 0
    },
    {
      "id": "273f0ac3-f8f6-4729-9b8e-fbc7e5f0ab6c",
      "data": [
        {
          "text": "turn up volume of music"
        }
      ],
      "isTemplate": false,
      "count": 0
    },
    {
      "id": "4c7188c6-c662-4312-b035-bd917c95c3b6",
      "data": [
        {
          "text": "raise your volume"
        }
      ],
      "isTemplate": false,
      "count": 0
    },
    {
      "id": "9e7deadc-36ab-4abf-81bc-c46b43e4710d",
      "data": [
        {
          "text": "can you turn up the volume on itunes"
        }
      ],
      "isTemplate": false,
      "count": 0
    },
    {
      "id": "48ffe96d-3a43-4894-a4d1-467a63b3b90c",
      "data": [
        {
          "text": "louder volume please"
        }
      ],
      "isTemplate": false,
      "count": 0
    },
    {
      "id": "24a5309f-8081-4c95-bed3-49ebbeecc592",
      "data": [
        {
          "text": "volume louder please"
        }
      ],
      "isTemplate": false,
      "count": 0
    },
    {
      "id": "7e47ff25-dafc-4f34-80d9-522c8b130119",
      "data": [
        {
          "text": "turn up media volume"
        }
      ],
      "isTemplate": false,
      "count": 0
    },
    {
      "id": "3cb813f6-9030-4218-a8bd-deb8820a91bc",
      "data": [
        {
          "text": "could you speak up"
        }
      ],
      "isTemplate": false,
      "count": 0
    },
    {
      "id": "32193d39-8cb5-420d-a774-12ff251c935e",
      "data": [
        {
          "text": "increase the volume of the speaker"
        }
      ],
      "isTemplate": false,
      "count": 0
    },
    {
      "id": "35b24167-d73d-48aa-8e2d-e1f059211ff4",
      "data": [
        {
          "text": "make the speaker volume on "
        },
        {
          "text": "maximum",
          "alias": "change_amount",
          "meta": "@change_amount",
          "userDefined": true
        }
      ],
      "isTemplate": false,
      "count": 0
    },
    {
      "id": "8bbbd765-ee34-4685-98db-5c5a40323a24",
      "data": [
        {
          "text": "i need to hear sound on my speakers"
        }
      ],
      "isTemplate": false,
      "count": 0
    },
    {
      "id": "23a883df-69ca-4b84-a740-bce7c6eaf7bd",
      "data": [
        {
          "text": "up the volume the sound is too low"
        }
      ],
      "isTemplate": false,
      "count": 0
    },
    {
      "id": "48c170e1-5d8b-4de7-9070-0617bab27d3b",
      "data": [
        {
          "text": "audio on"
        }
      ],
      "isTemplate": false,
      "count": 0
    },
    {
      "id": "00e7eb17-5e76-469f-8b1a-354efde54130",
      "data": [
        {
          "text": "speak louder"
        }
      ],
      "isTemplate": false,
      "count": 0
    },
    {
      "id": "dc55e90b-09ad-4f48-8918-845bd94c70cb",
      "data": [
        {
          "text": "i can't hear you"
        }
      ],
      "isTemplate": false,
      "count": 0
    },
    {
      "id": "99d948b8-2dd6-47d7-9802-cf318d2b850e",
      "data": [
        {
          "text": "turn up your volume"
        }
      ],
      "isTemplate": false,
      "count": 0
    },
    {
      "id": "39b363e4-f812-4f97-9c16-8feb7ff1ecb8",
      "data": [
        {
          "text": "turn up the volume"
        }
      ],
      "isTemplate": false,
      "count": 0
    },
    {
      "id": "8791403b-02b0-44e8-9f71-7deab6e3e3ba",
      "data": [
        {
          "text": "please increase the volume "
        },
        {
          "text": "to maximum",
          "alias": "change_amount",
          "meta": "@change_amount",
          "userDefined": true
        }
      ],
      "isTemplate": false,
      "count": 0
    },
    {
      "id": "536e7271-e5b5-4644-844c-3ce4de7c3626",
      "data": [
        {
          "text": "lower my "
        },
        {
          "text": "music player",
          "alias": "device_type",
          "meta": "@device_type",
          "userDefined": true
        },
        {
          "text": " volume "
        },
        {
          "text": "by fifty percent",
          "alias": "change_amount",
          "meta": "@change_amount",
          "userDefined": true
        },
        {
          "text": " of its current level"
        }
      ],
      "isTemplate": false,
      "count": 0
    },
    {
      "id": "f2e86ad5-c36b-4b69-baf3-20d342161043",
      "data": [
        {
          "text": "please turn my speakers on google"
        }
      ],
      "isTemplate": false,
      "count": 0
    },
    {
      "id": "41c9ddd4-f948-4b0e-8dcb-8dd8eb8c69cc",
      "data": [
        {
          "text": "turn up the volume on my speakers"
        }
      ],
      "isTemplate": false,
      "count": 0
    },
    {
      "id": "3c15172f-e6b2-4b7e-a94b-008c3457aff6",
      "data": [
        {
          "text": "increase the volume"
        }
      ],
      "isTemplate": false,
      "count": 0
    },
    {
      "id": "5dc7f52e-d8bb-4597-9302-5319689d1233",
      "data": [
        {
          "text": "please turn the volume to the "
        },
        {
          "text": "loudest",
          "alias": "change_amount",
          "meta": "@change_amount",
          "userDefined": true
        },
        {
          "text": " setting"
        }
      ],
      "isTemplate": false,
      "count": 0
    },
    {
      "id": "a049255b-3086-4610-95d4-9a9fb1d3dae2",
      "data": [
        {
          "text": "set the music volume "
        },
        {
          "text": "to ninety",
          "alias": "change_amount",
          "meta": "@change_amount",
          "userDefined": true
        }
      ],
      "isTemplate": false,
      "count": 0
    },
    {
      "id": "d893b4fc-5553-496b-9066-a39c15c702d1",
      "data": [
        {
          "text": "i need a high volume"
        }
      ],
      "isTemplate": false,
      "count": 0
    },
    {
      "id": "a844aef3-df4d-4958-b0fd-cefd0d63191c",
      "data": [
        {
          "text": "make sound louder"
        }
      ],
      "isTemplate": false,
      "count": 0
    },
    {
      "id": "4f13035d-a7a6-4f2f-97ff-ba9a22ef0240",
      "data": [
        {
          "text": "up"
        }
      ],
      "isTemplate": false,
      "count": 0
    },
    {
      "id": "e2545d2f-583e-43c9-b0ff-63ded9990ac2",
      "data": [
        {
          "text": "turn the volume up"
        }
      ],
      "isTemplate": false,
      "count": 0
    },
    {
      "id": "c6bf4ea8-2aa3-4036-8f22-3077e8e1d88b",
      "data": [
        {
          "text": "i can barely hear you"
        }
      ],
      "isTemplate": false,
      "count": 0
    },
    {
      "id": "58b38a60-d647-446d-87ae-bc15f0648281",
      "data": [
        {
          "text": "made media volume louder"
        }
      ],
      "isTemplate": false,
      "count": 0
    },
    {
      "id": "a0964557-7162-42a9-ba2e-1b8d4245c74d",
      "data": [
        {
          "text": "increase the volume "
        },
        {
          "text": "to max",
          "alias": "change_amount",
          "meta": "@change_amount",
          "userDefined": true
        },
        {
          "text": " please"
        }
      ],
      "isTemplate": false,
      "count": 0
    },
    {
      "id": "b33112f0-8780-4e04-9ac6-af14909261ed",
      "data": [
        {
          "text": "please decrease the volume of this song"
        }
      ],
      "isTemplate": false,
      "count": 0
    },
    {
      "id": "c04d6548-0b08-4e15-818b-3f3746121c89",
      "data": [
        {
          "text": "speak louder please"
        }
      ],
      "isTemplate": false,
      "count": 0
    },
    {
      "id": "fbf1bedb-4c4d-4c24-a650-02dd40de5b93",
      "data": [
        {
          "text": "please turn the music volume up"
        }
      ],
      "isTemplate": false,
      "count": 0
    },
    {
      "id": "f8056b23-7088-4d8b-9fa4-0012b48abec6",
      "data": [
        {
          "text": "i can't hear you can you say it again louder"
        }
      ],
      "isTemplate": false,
      "count": 0
    },
    {
      "id": "500c8469-a0fd-4685-a6cf-5d23f443abf5",
      "data": [
        {
          "text": "i can't hear just increase the volume"
        }
      ],
      "isTemplate": false,
      "count": 0
    },
    {
      "id": "4c5e6025-1e76-44b7-9828-5a6e2c25b55f",
      "data": [
        {
          "text": "please turn up the volume "
        },
        {
          "text": "to twenty one",
          "alias": "change_amount",
          "meta": "@change_amount",
          "userDefined": true
        }
      ],
      "isTemplate": false,
      "count": 0
    },
    {
      "id": "33d19896-f8b9-4a8a-8e30-c8dde30a0318",
      "data": [
        {
          "text": "increase volume "
        },
        {
          "text": "by two levels",
          "alias": "change_amount",
          "meta": "@change_amount",
          "userDefined": true
        }
      ],
      "isTemplate": false,
      "count": 0
    },
    {
      "id": "a6b4e0bb-6520-46d4-85ab-8e8f89fcfb22",
      "data": [
        {
          "text": "speaker volume increase"
        }
      ],
      "isTemplate": false,
      "count": 0
    },
    {
      "id": "44fb232b-26eb-4d28-ac50-ea162b008bd1",
      "data": [
        {
          "text": "the music volume should increase "
        },
        {
          "text": "to ninety",
          "alias": "change_amount",
          "meta": "@change_amount",
          "userDefined": true
        }
      ],
      "isTemplate": false,
      "count": 0
    },
    {
      "id": "2a2711f2-f2db-4343-95ff-4901b2aada0c",
      "data": [
        {
          "text": "turn the volume up on "
        },
        {
          "text": "music player",
          "alias": "device_type",
          "meta": "@device_type",
          "userDefined": true
        }
      ],
      "isTemplate": false,
      "count": 0
    },
    {
      "id": "ef928f2b-5e05-4114-b26d-f444d7d2bb74",
      "data": [
        {
          "text": "can you turn up the volume"
        }
      ],
      "isTemplate": false,
      "count": 0
    },
    {
      "id": "8ed51a8b-f21d-4891-9c2b-c01251eac9ce",
      "data": [
        {
          "text": "raise volume"
        }
      ],
      "isTemplate": false,
      "count": 0
    },
    {
      "id": "0319c3bf-c330-4501-9953-334282a7e114",
      "data": [
        {
          "text": "hey sound is low can you tune it up"
        }
      ],
      "isTemplate": false,
      "count": 0
    },
    {
      "id": "b5f7e625-339c-4616-8437-8116a63c3295",
      "data": [
        {
          "text": "turn up speakers"
        }
      ],
      "isTemplate": false,
      "count": 0
    },
    {
      "id": "398a0da4-255b-428e-90cb-8484d5276156",
      "data": [
        {
          "text": "increase the volume "
        },
        {
          "text": "to seventy percent",
          "alias": "change_amount",
          "meta": "@change_amount",
          "userDefined": true
        }
      ],
      "isTemplate": false,
      "count": 0
    },
    {
      "id": "26aa475f-3258-4f99-a643-e64fe146a4bf",
      "data": [
        {
          "text": "i need the volume to be louder"
        }
      ],
      "isTemplate": false,
      "count": 0
    },
    {
      "id": "be5b2a8e-8d36-41a7-8f98-62d36768e084",
      "data": [
        {
          "text": "increase the volume of the music "
        },
        {
          "text": "to ninety",
          "alias": "change_amount",
          "meta": "@change_amount",
          "userDefined": true
        }
      ],
      "isTemplate": false,
      "count": 0
    },
    {
      "id": "41366ab3-ac7a-43bd-b271-2a3698499175",
      "data": [
        {
          "text": "unmute the speaker now"
        }
      ],
      "isTemplate": false,
      "count": 0
    },
    {
      "id": "dbb999b4-fc44-4ab2-9864-717a385666b4",
      "data": [
        {
          "text": "please increase volume"
        }
      ],
      "isTemplate": false,
      "count": 0
    },
    {
      "id": "27d92af0-ac2a-489c-94c5-1d0052ed6df2",
      "data": [
        {
          "text": "could you speak "
        },
        {
          "text": "more softly",
          "alias": "change_amount",
          "meta": "@change_amount",
          "userDefined": true
        }
      ],
      "isTemplate": false,
      "count": 0
    },
    {
      "id": "1196fa96-0ae1-4086-8358-e828a64e943d",
      "data": [
        {
          "text": "i want volume on my speakers"
        }
      ],
      "isTemplate": false,
      "count": 0
    },
    {
      "id": "faf1def1-b9b0-455a-bd20-8147f9abce55",
      "data": [
        {
          "text": "raise the volume "
        },
        {
          "text": "to sixty",
          "alias": "change_amount",
          "meta": "@change_amount",
          "userDefined": true
        }
      ],
      "isTemplate": false,
      "count": 0
    },
    {
      "id": "7283f870-31db-49d0-8e68-81e4fcc55c69",
      "data": [
        {
          "text": "unmute"
        }
      ],
      "isTemplate": false,
      "count": 0
    },
    {
      "id": "cfdebbab-8435-4976-bbd9-2b07a5d0f1cd",
      "data": [
        {
          "text": "increase the volume so that i can hear it in other room"
        }
      ],
      "isTemplate": false,
      "count": 0
    },
    {
      "id": "9c5eb887-e147-4a5e-8916-8204764ee6fd",
      "data": [
        {
          "text": "loudly"
        }
      ],
      "isTemplate": false,
      "count": 0
    },
    {
      "id": "97339159-6111-4421-af5b-eab0668b60fa",
      "data": [
        {
          "text": "turn up "
        },
        {
          "text": "music",
          "alias": "media_type",
          "meta": "@media_type",
          "userDefined": true
        },
        {
          "text": " please"
        }
      ],
      "isTemplate": false,
      "count": 0
    },
    {
      "id": "c17ada4d-01e6-4761-a302-b554fc7bfdcf",
      "data": [
        {
          "text": "please turn up the speaker volume"
        }
      ],
      "isTemplate": false,
      "count": 0
    },
    {
      "id": "47b0a56c-139b-4e43-8670-b713534b2d12",
      "data": [
        {
          "text": "more volume please"
        }
      ],
      "isTemplate": false,
      "count": 0
    },
    {
      "id": "2677d5fa-ca99-4d6b-a948-e18f1edde82c",
      "data": [
        {
          "text": "change my "
        },
        {
          "text": "music player",
          "alias": "device_type",
          "meta": "@device_type",
          "userDefined": true
        },
        {
          "text": " volume "
        },
        {
          "text": "to eighty percent",
          "alias": "change_amount",
          "meta": "@change_amount",
          "userDefined": true
        }
      ],
      "isTemplate": false,
      "count": 0
    },
    {
      "id": "aef7d76d-fcc1-4042-9c83-1fe112196f15",
      "data": [
        {
          "text": "i couldn't hear you repeat that louder"
        }
      ],
      "isTemplate": false,
      "count": 0
    },
    {
      "id": "961b023a-a1b1-46ef-873d-086905aaba10",
      "data": [
        {
          "text": "turn up volume"
        }
      ],
      "isTemplate": false,
      "count": 0
    },
    {
      "id": "87a7f0be-3dcd-4662-8ba1-e03e5ae050f9",
      "data": [
        {
          "text": "turn up the volume on the music"
        }
      ],
      "isTemplate": false,
      "count": 0
    },
    {
      "id": "a6b3feab-06f0-4ae4-9fc5-d1aab52ca816",
      "data": [
        {
          "text": "increase the volume a bit"
        }
      ],
      "isTemplate": false,
      "count": 0
    },
    {
      "id": "32ad56a5-4d09-4826-80fa-45ef5d8fa647",
      "data": [
        {
          "text": "move the volume up a little"
        }
      ],
      "isTemplate": false,
      "count": 0
    },
    {
      "id": "2ff44935-ae25-457e-abac-0a56540dfce1",
      "data": [
        {
          "text": "can you turn the volume up"
        }
      ],
      "isTemplate": false,
      "count": 0
    },
    {
      "id": "e8c14413-42ae-4c19-9752-b51e088d60b5",
      "data": [
        {
          "text": "speak loudly"
        }
      ],
      "isTemplate": false,
      "count": 0
    },
    {
      "id": "7892236c-224d-4c04-8873-ce2d14f85f62",
      "data": [
        {
          "text": "turn volume up to highest level"
        }
      ],
      "isTemplate": false,
      "count": 0
    },
    {
      "id": "25f83ee3-c757-4ee6-b008-66fde4fb0a90",
      "data": [
        {
          "text": "please turn up the volume"
        }
      ],
      "isTemplate": false,
      "count": 0
    },
    {
      "id": "19828fd5-0b43-4345-b5dd-99d460a7563e",
      "data": [
        {
          "text": "play it louder"
        }
      ],
      "isTemplate": false,
      "count": 0
    },
    {
      "id": "1dad6d52-4ce2-49a1-90a3-ca030b545df2",
      "data": [
        {
          "text": "change the volume level "
        },
        {
          "text": "to nineteen",
          "alias": "change_amount",
          "meta": "@change_amount",
          "userDefined": true
        },
        {
          "text": " please"
        }
      ],
      "isTemplate": false,
      "count": 0
    },
    {
      "id": "95fa70af-2065-44a0-8cf4-6bea6b0dd059",
      "data": [
        {
          "text": "turn the sound up"
        }
      ],
      "isTemplate": false,
      "count": 0
    },
    {
      "id": "36f2f1fd-ce7f-4a14-b732-9012cebf0c75",
      "data": [
        {
          "text": "i am unable to hear you can you speak little loud"
        }
      ],
      "isTemplate": false,
      "count": 0
    },
    {
      "id": "0877f887-2e68-4e2e-a0f1-4de2a29822bd",
      "data": [
        {
          "text": "turn up"
        }
      ],
      "isTemplate": false,
      "count": 0
    },
    {
      "id": "6c1a9e5e-af61-410a-9d8d-a2c95927165f",
      "data": [
        {
          "text": "turn up the speakers"
        }
      ],
      "isTemplate": false,
      "count": 0
    },
    {
      "id": "e6789948-d811-4c93-994e-5e3bd954a7f8",
      "data": [
        {
          "text": "change the speaker volume "
        },
        {
          "text": "to sixty five percent",
          "alias": "change_amount",
          "meta": "@change_amount",
          "userDefined": true
        }
      ],
      "isTemplate": false,
      "count": 0
    },
    {
      "id": "53e45d1b-c545-44bb-8637-e88732621b0d",
      "data": [
        {
          "text": "can you turn up your volume"
        }
      ],
      "isTemplate": false,
      "count": 0
    },
    {
      "id": "b3aa36a9-6f9e-462f-a2da-acf648ba8fec",
      "data": [
        {
          "text": "increase volume"
        }
      ],
      "isTemplate": false,
      "count": 0
    },
    {
      "id": "1f888f60-2fc9-4cb7-9a34-3468fcf9a24e",
      "data": [
        {
          "text": "please speak up"
        }
      ],
      "isTemplate": false,
      "count": 0
    },
    {
      "id": "60330066-ce37-4bcb-b717-5ed0be0e51eb",
      "data": [
        {
          "text": "get louder"
        }
      ],
      "isTemplate": false,
      "count": 0
    },
    {
      "id": "8f82f8c9-fd20-4c00-80f6-ec4b9544a192",
      "data": [
        {
          "text": "increase the volume "
        },
        {
          "text": "to fifty",
          "alias": "change_amount",
          "meta": "@change_amount",
          "userDefined": true
        }
      ],
      "isTemplate": false,
      "count": 0
    },
    {
      "id": "5b34b1f1-77c2-4ce6-8744-158e847f808f",
      "data": [
        {
          "text": "increase volume "
        },
        {
          "text": "by one",
          "alias": "change_amount",
          "meta": "@change_amount",
          "userDefined": true
        }
      ],
      "isTemplate": false,
      "count": 0
    },
    {
      "id": "8f5742c9-73fd-469f-86b4-851c983b09a2",
      "data": [
        {
          "text": "unmute after"
        }
      ],
      "isTemplate": false,
      "count": 0
    },
    {
      "id": "748f83f2-b9d5-4aa5-aea0-ba4108d89b8e",
      "data": [
        {
          "text": "could you speak louder"
        }
      ],
      "isTemplate": false,
      "count": 0
    },
    {
      "id": "495c1bf3-35de-4d4a-a9ab-1d3456b3cacf",
      "data": [
        {
          "text": "increase the volume of the "
        },
        {
          "text": "left speaker",
          "alias": "device_type",
          "meta": "@device_type",
          "userDefined": true
        },
        {
          "text": " "
        },
        {
          "text": "by ten",
          "alias": "change_amount",
          "meta": "@change_amount",
          "userDefined": true
        }
      ],
      "isTemplate": false,
      "count": 0
    },
    {
      "id": "ca758f9c-f5ed-4887-a894-4496a5a732fa",
      "data": [
        {
          "text": "can you turn it up a little"
        }
      ],
      "isTemplate": false,
      "count": 0
    },
    {
      "id": "f46f15de-3cbe-43eb-b97c-ec56b5de74b6",
      "data": [
        {
          "text": "can you speak louder"
        }
      ],
      "isTemplate": false,
      "count": 0
    },
    {
      "id": "952dac17-3bda-4167-bf7c-7613567fd420",
      "data": [
        {
          "text": "louder please"
        }
      ],
      "isTemplate": false,
      "count": 0
    },
    {
      "id": "d828e15b-c1c3-4c07-9c70-0cc3e0b66b14",
      "data": [
        {
          "text": "turn up sound"
        }
      ],
      "isTemplate": false,
      "count": 0
    },
    {
      "id": "185fbd47-acb1-4a3f-b061-2a07cfece139",
      "data": [
        {
          "text": "i need you to say that last information again but much louder"
        }
      ],
      "isTemplate": false,
      "count": 0
    }
  ],
  "id": "600385d3-20d0-4447-9dc2-097f804ec1ed",
  "name": "audio_volume_up",
  "auto": true,
  "contexts": [],
  "responses": [
    {
      "resetContexts": false,
      "affectedContexts": [],
      "parameters": [
        {
          "dataType": "@change_amount",
          "name": "change_amount",
          "value": "$change_amount"
        },
        {
          "dataType": "@device_type",
          "name": "device_type",
          "value": "$device_type"
        },
        {
          "dataType": "@media_type",
          "name": "media_type",
          "value": "$media_type"
        },
        {
          "dataType": "@song_name",
          "name": "song_name",
          "value": "$song_name"
        }
      ],
      "messages": [
        {
          "type": 0,
          "speech": []
        }
      ]
    }
  ],
  "webhookUsed": false,
  "webhookForSlotFilling": false,
  "fallbackIntent": false,
  "events": []
}
