{
  "userSays": [
    {
      "id": "de672818-23fc-42fc-959a-9fe2fd22a315",
      "data": [
        {
          "text": "remove the next event on my calendar"
        }
      ],
      "isTemplate": false,
      "count": 0
    },
    {
      "id": "be6ad46f-0b51-405c-826e-8d9c840473a4",
      "data": [
        {
          "text": "format the calendar"
        }
      ],
      "isTemplate": false,
      "count": 0
    },
    {
      "id": "c8583687-ab39-49fc-8ece-d2084ff8414f",
      "data": [
        {
          "text": "remove the "
        },
        {
          "text": "board meeting",
          "alias": "event_name",
          "meta": "@event_name",
          "userDefined": true
        },
        {
          "text": " and reschedule for next "
        },
        {
          "text": "wednesday",
          "alias": "date",
          "meta": "@date",
          "userDefined": true
        }
      ],
      "isTemplate": false,
      "count": 0
    },
    {
      "id": "9d870896-6c22-48c2-8944-f9d37a5f172c",
      "data": [
        {
          "text": "delete event from mine"
        }
      ],
      "isTemplate": false,
      "count": 0
    },
    {
      "id": "caba6773-fd36-490f-ad3e-cbdbfec7b6f5",
      "data": [
        {
          "text": "cancel the event "
        },
        {
          "text": "valentine's day",
          "alias": "event_name",
          "meta": "@event_name",
          "userDefined": true
        },
        {
          "text": " from the calendar"
        }
      ],
      "isTemplate": false,
      "count": 0
    },
    {
      "id": "55ea12ad-a281-4c66-94e1-d5ea53ad328d",
      "data": [
        {
          "text": "remove my "
        },
        {
          "text": "meeting",
          "alias": "event_name",
          "meta": "@event_name",
          "userDefined": true
        },
        {
          "text": " today at "
        },
        {
          "text": "one pm",
          "alias": "time",
          "meta": "@time",
          "userDefined": true
        }
      ],
      "isTemplate": false,
      "count": 0
    },
    {
      "id": "5f6820ec-233d-4cbf-ae0b-ace192212a9a",
      "data": [
        {
          "text": "i no longer need to see the "
        },
        {
          "text": "doctor",
          "alias": "event_name",
          "meta": "@event_name",
          "userDefined": true
        },
        {
          "text": " can that event be removed"
        }
      ],
      "isTemplate": false,
      "count": 0
    },
    {
      "id": "af99103b-db29-48f2-8aa0-056616ca28a6",
      "data": [
        {
          "text": "please remove "
        },
        {
          "text": "march nineteenth",
          "alias": "date",
          "meta": "@date",
          "userDefined": true
        },
        {
          "text": "'s scheduled event"
        }
      ],
      "isTemplate": false,
      "count": 0
    },
    {
      "id": "413817d8-f752-4c2c-96db-11002c5c9956",
      "data": [
        {
          "text": "make sure there is no events on my calendar"
        }
      ],
      "isTemplate": false,
      "count": 0
    },
    {
      "id": "5774a686-ee21-4743-b667-1736cfaf8149",
      "data": [
        {
          "text": "remove all the events on my calendar"
        }
      ],
      "isTemplate": false,
      "count": 0
    },
    {
      "id": "835d14ad-3146-4cba-a2e8-bbe6b5045801",
      "data": [
        {
          "text": "delete my "
        },
        {
          "text": "meeting",
          "alias": "event_name",
          "meta": "@event_name",
          "userDefined": true
        },
        {
          "text": " event for "
        },
        {
          "text": "march nineteen",
          "alias": "date",
          "meta": "@date",
          "userDefined": true
        },
        {
          "text": " at "
        },
        {
          "text": "one pm",
          "alias": "time",
          "meta": "@time",
          "userDefined": true
        }
      ],
      "isTemplate": false,
      "count": 0
    },
    {
      "id": "9d8819aa-ea12-4d5a-babf-64028e085035",
      "data": [
        {
          "text": "remove upcoming task"
        }
      ],
      "isTemplate": false,
      "count": 0
    },
    {
      "id": "7a9a7c65-312f-434f-9c76-e708db32c0a4",
      "data": [
        {
          "text": "remove "
        },
        {
          "text": "emma",
          "alias": "person",
          "meta": "@person",
          "userDefined": true
        },
        {
          "text": "'s "
        },
        {
          "text": "birthday",
          "alias": "event_name",
          "meta": "@event_name",
          "userDefined": true
        },
        {
          "text": " from events"
        }
      ],
      "isTemplate": false,
      "count": 0
    },
    {
      "id": "113b02a0-b7c9-45d8-a254-32bc5673e9c4",
      "data": [
        {
          "text": "in my calendar delete all of my "
        },
        {
          "text": "golf events",
          "alias": "event_name",
          "meta": "@event_name",
          "userDefined": true
        },
        {
          "text": " for the current "
        },
        {
          "text": "month",
          "alias": "date",
          "meta": "@date",
          "userDefined": true
        }
      ],
      "isTemplate": false,
      "count": 0
    },
    {
      "id": "6610207d-4599-4db3-b174-0b963ba244e1",
      "data": [
        {
          "text": "erase calendar events"
        }
      ],
      "isTemplate": false,
      "count": 0
    },
    {
      "id": "7b75c7eb-e65f-40bc-a9a9-d196f981b25d",
      "data": [
        {
          "text": "take "
        },
        {
          "text": "lunch meeting",
          "alias": "event_name",
          "meta": "@event_name",
          "userDefined": true
        },
        {
          "text": " off my calendar"
        }
      ],
      "isTemplate": false,
      "count": 0
    },
    {
      "id": "4e753197-7b60-4c06-8c8a-fc1eec3fef07",
      "data": [
        {
          "text": "delete all my events for "
        },
        {
          "text": "tomorrow",
          "alias": "date",
          "meta": "@date",
          "userDefined": true
        }
      ],
      "isTemplate": false,
      "count": 0
    },
    {
      "id": "d7433fc1-3e36-4fed-becb-9d5333c19666",
      "data": [
        {
          "text": "delete the "
        },
        {
          "text": "party",
          "alias": "event_name",
          "meta": "@event_name",
          "userDefined": true
        },
        {
          "text": " on "
        },
        {
          "text": "june first",
          "alias": "date",
          "meta": "@date",
          "userDefined": true
        },
        {
          "text": " from my calendar"
        }
      ],
      "isTemplate": false,
      "count": 0
    },
    {
      "id": "b0f86dc8-fccd-45ca-922e-1ce6651329f9",
      "data": [
        {
          "text": "can to please clear my calendar of all events"
        }
      ],
      "isTemplate": false,
      "count": 0
    },
    {
      "id": "07c7785a-5be6-42d7-be94-cf4f87089e74",
      "data": [
        {
          "text": "remove next "
        },
        {
          "text": "meeting",
          "alias": "event_name",
          "meta": "@event_name",
          "userDefined": true
        },
        {
          "text": " "
        },
        {
          "text": "today",
          "alias": "date",
          "meta": "@date",
          "userDefined": true
        },
        {
          "text": " in my calendar"
        }
      ],
      "isTemplate": false,
      "count": 0
    },
    {
      "id": "84671ab8-48a3-4506-9381-fed9a5a43369",
      "data": [
        {
          "text": "cancel the "
        },
        {
          "text": "breakfast",
          "alias": "meal_type",
          "meta": "@meal_type",
          "userDefined": true
        },
        {
          "text": " at "
        },
        {
          "text": "tiffany's house",
          "alias": "place_name",
          "meta": "@place_name",
          "userDefined": true
        }
      ],
      "isTemplate": false,
      "count": 0
    },
    {
      "id": "ad3a01c8-8e94-4208-a63e-d89fb9ea95d0",
      "data": [
        {
          "text": "remove the "
        },
        {
          "text": "fundraiser for dolphines",
          "alias": "event_name",
          "meta": "@event_name",
          "userDefined": true
        },
        {
          "text": " in "
        },
        {
          "text": "april",
          "alias": "date",
          "meta": "@date",
          "userDefined": true
        }
      ],
      "isTemplate": false,
      "count": 0
    },
    {
      "id": "f7e2ba86-7a5c-4a15-9334-5345c9f8204c",
      "data": [
        {
          "text": "please clear out my calendar completely"
        }
      ],
      "isTemplate": false,
      "count": 0
    },
    {
      "id": "dd6fe146-8301-4d38-bd92-17ad3faba43f",
      "data": [
        {
          "text": "delete "
        },
        {
          "text": "meeting",
          "alias": "event_name",
          "meta": "@event_name",
          "userDefined": true
        }
      ],
      "isTemplate": false,
      "count": 0
    },
    {
      "id": "8854576f-b8b5-47c9-a810-9bb2b1e4b34a",
      "data": [
        {
          "text": "can you take off the next event on my calendar"
        }
      ],
      "isTemplate": false,
      "count": 0
    },
    {
      "id": "b12b9559-dd60-4a9d-bc19-57dec238eaeb",
      "data": [
        {
          "text": "remove the "
        },
        {
          "text": "doctor's appointment",
          "alias": "event_name",
          "meta": "@event_name",
          "userDefined": true
        },
        {
          "text": " i added to my calendar for "
        },
        {
          "text": "february twelfth",
          "alias": "date",
          "meta": "@date",
          "userDefined": true
        },
        {
          "text": " at "
        },
        {
          "text": "nine am",
          "alias": "time",
          "meta": "@time",
          "userDefined": true
        }
      ],
      "isTemplate": false,
      "count": 0
    },
    {
      "id": "7bc7d13f-3efb-427e-af4a-7e63efd6bc41",
      "data": [
        {
          "text": "hey olly on the "
        },
        {
          "text": "twentieth",
          "alias": "date",
          "meta": "@date",
          "userDefined": true
        },
        {
          "text": " clear my calendar"
        }
      ],
      "isTemplate": false,
      "count": 0
    },
    {
      "id": "7ac7a9e0-24e6-4f30-914c-4ab26a618077",
      "data": [
        {
          "text": "cancel my event on "
        },
        {
          "text": "june nineteenth",
          "alias": "date",
          "meta": "@date",
          "userDefined": true
        }
      ],
      "isTemplate": false,
      "count": 0
    },
    {
      "id": "be900bc0-7458-4cbc-9c3a-e6cca5737c58",
      "data": [
        {
          "text": "remove all upcoming events please"
        }
      ],
      "isTemplate": false,
      "count": 0
    },
    {
      "id": "411ac78a-a928-4314-abaa-aef15e7c9cc1",
      "data": [
        {
          "text": "clean my calendar"
        }
      ],
      "isTemplate": false,
      "count": 0
    },
    {
      "id": "80cf5503-8984-40b4-ae3a-e95249e33baa",
      "data": [
        {
          "text": "remove all events from my calendar"
        }
      ],
      "isTemplate": false,
      "count": 0
    },
    {
      "id": "d96059f0-ac11-4f86-b37e-091160bcffe4",
      "data": [
        {
          "text": "hi olly please cancel all the programs for "
        },
        {
          "text": "friday",
          "alias": "date",
          "meta": "@date",
          "userDefined": true
        }
      ],
      "isTemplate": false,
      "count": 0
    },
    {
      "id": "0d1e69c8-ca5e-4a41-a4d6-c2d74bbe1d69",
      "data": [
        {
          "text": "i don't want to attend the "
        },
        {
          "text": "dinner",
          "alias": "meal_type",
          "meta": "@meal_type",
          "userDefined": true
        },
        {
          "text": " on "
        },
        {
          "text": "march first",
          "alias": "date",
          "meta": "@date",
          "userDefined": true
        },
        {
          "text": " any more so could you remove it from my agenda"
        }
      ],
      "isTemplate": false,
      "count": 0
    },
    {
      "id": "75cd52f0-88db-40fc-80eb-2e7ce4c71f95",
      "data": [
        {
          "text": "please delete "
        },
        {
          "text": "all meetings",
          "alias": "event_name",
          "meta": "@event_name",
          "userDefined": true
        },
        {
          "text": " of "
        },
        {
          "text": "today",
          "alias": "date",
          "meta": "@date",
          "userDefined": true
        },
        {
          "text": " "
        },
        {
          "text": "after seven pm",
          "alias": "time",
          "meta": "@time",
          "userDefined": true
        }
      ],
      "isTemplate": false,
      "count": 0
    },
    {
      "id": "57b89469-743a-4801-b694-e28d35684134",
      "data": [
        {
          "text": "cancel "
        },
        {
          "text": "business meeting",
          "alias": "event_name",
          "meta": "@event_name",
          "userDefined": true
        },
        {
          "text": " on "
        },
        {
          "text": "wednesday",
          "alias": "date",
          "meta": "@date",
          "userDefined": true
        }
      ],
      "isTemplate": false,
      "count": 0
    },
    {
      "id": "4af64ca6-d349-4cb2-b66d-0292bd4fb680",
      "data": [
        {
          "text": "delete "
        },
        {
          "text": "appointment",
          "alias": "event_name",
          "meta": "@event_name",
          "userDefined": true
        },
        {
          "text": " at time"
        }
      ],
      "isTemplate": false,
      "count": 0
    },
    {
      "id": "48536e43-8f3f-491c-85c6-7eb0fc3fd846",
      "data": [
        {
          "text": "delete my "
        },
        {
          "text": "dentist appointment",
          "alias": "event_name",
          "meta": "@event_name",
          "userDefined": true
        }
      ],
      "isTemplate": false,
      "count": 0
    },
    {
      "id": "fcf87525-095f-4d3f-b57c-34f2dc6540f3",
      "data": [
        {
          "text": "erase my next calendar event"
        }
      ],
      "isTemplate": false,
      "count": 0
    },
    {
      "id": "a8aec150-2ec6-419b-8070-e290c8a2a32f",
      "data": [
        {
          "text": "i want you to remove this event"
        }
      ],
      "isTemplate": false,
      "count": 0
    },
    {
      "id": "4d09df08-6af0-4c26-b065-a7cce2ee71fd",
      "data": [
        {
          "text": "remove "
        },
        {
          "text": "today",
          "alias": "date",
          "meta": "@date",
          "userDefined": true
        },
        {
          "text": "'s "
        },
        {
          "text": "meeting",
          "alias": "event_name",
          "meta": "@event_name",
          "userDefined": true
        },
        {
          "text": " at "
        },
        {
          "text": "evening",
          "alias": "timeofday",
          "meta": "@timeofday",
          "userDefined": true
        }
      ],
      "isTemplate": false,
      "count": 0
    },
    {
      "id": "afc6a833-f986-462f-a2ae-fda82a37d5a7",
      "data": [
        {
          "text": "delete all my "
        },
        {
          "text": "appointments",
          "alias": "event_name",
          "meta": "@event_name",
          "userDefined": true
        },
        {
          "text": " for "
        },
        {
          "text": "today",
          "alias": "date",
          "meta": "@date",
          "userDefined": true
        }
      ],
      "isTemplate": false,
      "count": 0
    },
    {
      "id": "ddb3ca51-7727-404c-9462-1d4e9656b7be",
      "data": [
        {
          "text": "clear all events for "
        },
        {
          "text": "this month",
          "alias": "date",
          "meta": "@date",
          "userDefined": true
        }
      ],
      "isTemplate": false,
      "count": 0
    },
    {
      "id": "b44cee14-c27c-4b7c-920d-b885989f5d43",
      "data": [
        {
          "text": "cancel all my "
        },
        {
          "text": "appointments",
          "alias": "event_name",
          "meta": "@event_name",
          "userDefined": true
        }
      ],
      "isTemplate": false,
      "count": 0
    },
    {
      "id": "f9dbbb77-304a-4d4a-8d31-07e5cd941c4c",
      "data": [
        {
          "text": "remove calendar events for "
        },
        {
          "text": "this week",
          "alias": "date",
          "meta": "@date",
          "userDefined": true
        }
      ],
      "isTemplate": false,
      "count": 0
    },
    {
      "id": "a417383d-3d47-478a-be38-02ea329444a3",
      "data": [
        {
          "text": "remove sample "
        },
        {
          "text": "meeting",
          "alias": "event_name",
          "meta": "@event_name",
          "userDefined": true
        },
        {
          "text": " from "
        },
        {
          "text": "calendar app",
          "alias": "app_name",
          "meta": "@app_name",
          "userDefined": true
        }
      ],
      "isTemplate": false,
      "count": 0
    },
    {
      "id": "b4a01bf4-eec4-4c91-bb13-826594a5d6ea",
      "data": [
        {
          "text": "whatever the next event is in the calendar delete it"
        }
      ],
      "isTemplate": false,
      "count": 0
    },
    {
      "id": "4585898c-88b2-4907-bdc5-0f9216fc5fc4",
      "data": [
        {
          "text": "get rid of everything on my calendar"
        }
      ],
      "isTemplate": false,
      "count": 0
    },
    {
      "id": "4ff9f620-1334-4fd7-a2ef-5696bc764907",
      "data": [
        {
          "text": "please delete this calendar event"
        }
      ],
      "isTemplate": false,
      "count": 0
    },
    {
      "id": "1a64ac12-a2da-41ec-82da-b36e1827c9b1",
      "data": [
        {
          "text": "hi olly please remove the "
        },
        {
          "text": "birthday",
          "alias": "event_name",
          "meta": "@event_name",
          "userDefined": true
        },
        {
          "text": " event on "
        },
        {
          "text": "coming sunday",
          "alias": "date",
          "meta": "@date",
          "userDefined": true
        }
      ],
      "isTemplate": false,
      "count": 0
    },
    {
      "id": "0df7f9c8-8058-4639-b2d1-3cfbabf7c35a",
      "data": [
        {
          "text": "remove all the reminders from the calendar"
        }
      ],
      "isTemplate": false,
      "count": 0
    },
    {
      "id": "b9776327-5bf8-42da-b12c-e916df9ce5da",
      "data": [
        {
          "text": "remove all the events and schedules"
        }
      ],
      "isTemplate": false,
      "count": 0
    },
    {
      "id": "68e2feca-9a30-47b3-ac31-440d918a2915",
      "data": [
        {
          "text": "erase that from my calendar"
        }
      ],
      "isTemplate": false,
      "count": 0
    },
    {
      "id": "3cbac160-8bd0-427d-8bc7-04752ec13a84",
      "data": [
        {
          "text": "delete my next scheduled event please"
        }
      ],
      "isTemplate": false,
      "count": 0
    },
    {
      "id": "e01cee49-c291-4029-8937-51f84949ac2b",
      "data": [
        {
          "text": "cancel "
        },
        {
          "text": "tomorrow",
          "alias": "date",
          "meta": "@date",
          "userDefined": true
        },
        {
          "text": "'s "
        },
        {
          "text": "meeting",
          "alias": "event_name",
          "meta": "@event_name",
          "userDefined": true
        }
      ],
      "isTemplate": false,
      "count": 0
    },
    {
      "id": "62bfdff4-d1a9-4e24-8816-a015c16b513a",
      "data": [
        {
          "text": "can you delete all events from my calendar"
        }
      ],
      "isTemplate": false,
      "count": 0
    },
    {
      "id": "7075f6a2-7316-49ed-9744-fadf83b4cee9",
      "data": [
        {
          "text": "delete event for "
        },
        {
          "text": "tuesday",
          "alias": "date",
          "meta": "@date",
          "userDefined": true
        }
      ],
      "isTemplate": false,
      "count": 0
    },
    {
      "id": "cc7543a7-f497-45a2-b68d-23ddc8440019",
      "data": [
        {
          "text": "clear my day on the "
        },
        {
          "text": "twenty ninth",
          "alias": "date",
          "meta": "@date",
          "userDefined": true
        }
      ],
      "isTemplate": false,
      "count": 0
    },
    {
      "id": "0442bcf6-44f9-45a8-8dcc-495dcef6ad9d",
      "data": [
        {
          "text": "delete "
        },
        {
          "text": "lunch",
          "alias": "meal_type",
          "meta": "@meal_type",
          "userDefined": true
        },
        {
          "text": " "
        },
        {
          "text": "tomorrow",
          "alias": "date",
          "meta": "@date",
          "userDefined": true
        }
      ],
      "isTemplate": false,
      "count": 0
    },
    {
      "id": "a97d5c55-9dd9-43ba-bacf-0270f6445cb2",
      "data": [
        {
          "text": "clear everything from the calendar"
        }
      ],
      "isTemplate": false,
      "count": 0
    },
    {
      "id": "90d30b22-8f0c-4a27-8511-bbde607e1048",
      "data": [
        {
          "text": "delete the events from the calendar on "
        },
        {
          "text": "twenty eighth march",
          "alias": "date",
          "meta": "@date",
          "userDefined": true
        }
      ],
      "isTemplate": false,
      "count": 0
    },
    {
      "id": "77b7085d-dca0-42b2-a358-0c3c045fdaa0",
      "data": [
        {
          "text": "remove the event from "
        },
        {
          "text": "monday",
          "alias": "date",
          "meta": "@date",
          "userDefined": true
        }
      ],
      "isTemplate": false,
      "count": 0
    },
    {
      "id": "0ee074af-d3d8-454c-ac1b-1b0cc6b96986",
      "data": [
        {
          "text": "take off the "
        },
        {
          "text": "doctor's appointment",
          "alias": "event_name",
          "meta": "@event_name",
          "userDefined": true
        },
        {
          "text": " on "
        },
        {
          "text": "march twentieth",
          "alias": "date",
          "meta": "@date",
          "userDefined": true
        }
      ],
      "isTemplate": false,
      "count": 0
    },
    {
      "id": "2e60c122-da37-4841-bf33-781a428221de",
      "data": [
        {
          "text": "cancel "
        },
        {
          "text": "meeting",
          "alias": "event_name",
          "meta": "@event_name",
          "userDefined": true
        },
        {
          "text": " at "
        },
        {
          "text": "three",
          "alias": "time",
          "meta": "@time",
          "userDefined": true
        }
      ],
      "isTemplate": false,
      "count": 0
    },
    {
      "id": "e934cea1-f59f-41c8-b7fa-11f94078925d",
      "data": [
        {
          "text": "delete all "
        },
        {
          "text": "recurring",
          "alias": "general_frequency",
          "meta": "@general_frequency",
          "userDefined": true
        },
        {
          "text": " "
        },
        {
          "text": "staff meetings",
          "alias": "event_name",
          "meta": "@event_name",
          "userDefined": true
        }
      ],
      "isTemplate": false,
      "count": 0
    },
    {
      "id": "e04c7e04-015d-46bf-a371-9c0fee0c1fdb",
      "data": [
        {
          "text": "remove all the events of "
        },
        {
          "text": "last month",
          "alias": "date",
          "meta": "@date",
          "userDefined": true
        },
        {
          "text": " from the calendar"
        }
      ],
      "isTemplate": false,
      "count": 0
    },
    {
      "id": "eb1697d0-b307-491a-8d2a-e796d0ec82e5",
      "data": [
        {
          "text": "i'm not doing thing "
        },
        {
          "text": "this week",
          "alias": "date",
          "meta": "@date",
          "userDefined": true
        }
      ],
      "isTemplate": false,
      "count": 0
    },
    {
      "id": "d76e4a61-3ca8-4ca1-b2e5-e6330e10644d",
      "data": [
        {
          "text": "delete all events for the "
        },
        {
          "text": "next five days",
          "alias": "date",
          "meta": "@date",
          "userDefined": true
        }
      ],
      "isTemplate": false,
      "count": 0
    },
    {
      "id": "b6e1152a-09cc-4df5-9d6e-babbeeedc108",
      "data": [
        {
          "text": "delete all the events of "
        },
        {
          "text": "today",
          "alias": "date",
          "meta": "@date",
          "userDefined": true
        }
      ],
      "isTemplate": false,
      "count": 0
    },
    {
      "id": "72c552f4-51b6-4341-8d26-f0304e790bb2",
      "data": [
        {
          "text": "delete that"
        }
      ],
      "isTemplate": false,
      "count": 0
    },
    {
      "id": "613c9a74-2968-47f8-b875-5c9fd4aacbee",
      "data": [
        {
          "text": "can you delete the "
        },
        {
          "text": "dentist appointment",
          "alias": "event_name",
          "meta": "@event_name",
          "userDefined": true
        }
      ],
      "isTemplate": false,
      "count": 0
    },
    {
      "id": "742c8073-8fb5-4177-8a90-13cc334ea187",
      "data": [
        {
          "text": "please remove my next event"
        }
      ],
      "isTemplate": false,
      "count": 0
    },
    {
      "id": "3a827774-b00a-4cc4-9e78-8b46578eecdf",
      "data": [
        {
          "text": "delete my "
        },
        {
          "text": "meeting",
          "alias": "event_name",
          "meta": "@event_name",
          "userDefined": true
        },
        {
          "text": " for "
        },
        {
          "text": "one pm",
          "alias": "time",
          "meta": "@time",
          "userDefined": true
        },
        {
          "text": " on "
        },
        {
          "text": "march nineteenth",
          "alias": "date",
          "meta": "@date",
          "userDefined": true
        }
      ],
      "isTemplate": false,
      "count": 0
    },
    {
      "id": "a90e59e7-6b06-43de-b4a4-73b996c270a4",
      "data": [
        {
          "text": "i need to cancel my "
        },
        {
          "text": "rsvp for dinner",
          "alias": "event_name",
          "meta": "@event_name",
          "userDefined": true
        },
        {
          "text": " this evening can you remove it on my calendar as well"
        }
      ],
      "isTemplate": false,
      "count": 0
    },
    {
      "id": "660d8102-7599-4479-a774-c840f4e13cb5",
      "data": [
        {
          "text": "remove all the events in my calendar"
        }
      ],
      "isTemplate": false,
      "count": 0
    },
    {
      "id": "cb055873-717d-4921-a789-cc54289b91ff",
      "data": [
        {
          "text": "can you deleted the current event"
        }
      ],
      "isTemplate": false,
      "count": 0
    },
    {
      "id": "c0ad7630-9938-4a6c-9c61-83e8519daf10",
      "data": [
        {
          "text": "event remove"
        }
      ],
      "isTemplate": false,
      "count": 0
    },
    {
      "id": "176dabb5-aebf-4f5a-89ab-d3ae27ea1163",
      "data": [
        {
          "text": "please delete next "
        },
        {
          "text": "meeting",
          "alias": "event_name",
          "meta": "@event_name",
          "userDefined": true
        },
        {
          "text": " with "
        },
        {
          "text": "rajesh",
          "alias": "person",
          "meta": "@person",
          "userDefined": true
        }
      ],
      "isTemplate": false,
      "count": 0
    },
    {
      "id": "aa7ae2c0-f6d2-4af4-bc58-36ea19c2ede4",
      "data": [
        {
          "text": "remove meeting for "
        },
        {
          "text": "wednesday",
          "alias": "date",
          "meta": "@date",
          "userDefined": true
        },
        {
          "text": " "
        },
        {
          "text": "morning",
          "alias": "timeofday",
          "meta": "@timeofday",
          "userDefined": true
        }
      ],
      "isTemplate": false,
      "count": 0
    },
    {
      "id": "41076a15-2dd0-486b-926c-f177f1f7d68a",
      "data": [
        {
          "text": "dismiss my next event"
        }
      ],
      "isTemplate": false,
      "count": 0
    },
    {
      "id": "bd01f269-d310-4e7e-9794-43b3896c3d3f",
      "data": [
        {
          "text": "give some of delete in "
        },
        {
          "text": "today",
          "alias": "date",
          "meta": "@date",
          "userDefined": true
        },
        {
          "text": " events"
        }
      ],
      "isTemplate": false,
      "count": 0
    },
    {
      "id": "8b6623c4-c3a2-4cb4-a7b4-560ff84dbe5e",
      "data": [
        {
          "text": "remove my "
        },
        {
          "text": "car payment",
          "alias": "event_name",
          "meta": "@event_name",
          "userDefined": true
        },
        {
          "text": " on the "
        },
        {
          "text": "fifteenth",
          "alias": "date",
          "meta": "@date",
          "userDefined": true
        },
        {
          "text": " from my calendar"
        }
      ],
      "isTemplate": false,
      "count": 0
    },
    {
      "id": "a59febe4-899a-4d7d-983b-cfcb6730960d",
      "data": [
        {
          "text": "delete the next event in the calendar"
        }
      ],
      "isTemplate": false,
      "count": 0
    },
    {
      "id": "7fbd71c9-4ae9-48a6-9e39-d4061140c2c3",
      "data": [
        {
          "text": "cancel all "
        },
        {
          "text": "meetings",
          "alias": "event_name",
          "meta": "@event_name",
          "userDefined": true
        },
        {
          "text": " for "
        },
        {
          "text": "today",
          "alias": "date",
          "meta": "@date",
          "userDefined": true
        }
      ],
      "isTemplate": false,
      "count": 0
    },
    {
      "id": "24023f8f-b821-40e2-8dae-a7b53892c923",
      "data": [
        {
          "text": "clear all events from "
        },
        {
          "text": "march seven",
          "alias": "date",
          "meta": "@date",
          "userDefined": true
        }
      ],
      "isTemplate": false,
      "count": 0
    },
    {
      "id": "8a7fef5e-b461-4505-9143-3bc3d55547dd",
      "data": [
        {
          "text": "remove my calendar event at "
        },
        {
          "text": "one pm",
          "alias": "time",
          "meta": "@time",
          "userDefined": true
        },
        {
          "text": " "
        },
        {
          "text": "today",
          "alias": "date",
          "meta": "@date",
          "userDefined": true
        }
      ],
      "isTemplate": false,
      "count": 0
    },
    {
      "id": "868fe11a-34f1-4994-97ca-2f15b8c414c0",
      "data": [
        {
          "text": "please remove the "
        },
        {
          "text": "appointment",
          "alias": "event_name",
          "meta": "@event_name",
          "userDefined": true
        },
        {
          "text": " which i have made with "
        },
        {
          "text": "mrjim",
          "alias": "person",
          "meta": "@person",
          "userDefined": true
        }
      ],
      "isTemplate": false,
      "count": 0
    },
    {
      "id": "afb56be2-4393-4c50-bd01-20b81078fc4c",
      "data": [
        {
          "text": "can you remove that on my calendar"
        }
      ],
      "isTemplate": false,
      "count": 0
    },
    {
      "id": "bf6251fc-f8e1-4f33-8945-628e266ae40c",
      "data": [
        {
          "text": "please delete my "
        },
        {
          "text": "lunch",
          "alias": "meal_type",
          "meta": "@meal_type",
          "userDefined": true
        },
        {
          "text": " date from the "
        },
        {
          "text": "march twenty third",
          "alias": "date",
          "meta": "@date",
          "userDefined": true
        },
        {
          "text": " schedule"
        }
      ],
      "isTemplate": false,
      "count": 0
    },
    {
      "id": "7f2b8f03-92db-4d9f-9f80-9bcc888d91b5",
      "data": [
        {
          "text": "list all events and delete"
        }
      ],
      "isTemplate": false,
      "count": 0
    },
    {
      "id": "bab8082c-4f72-405d-b9d4-7563f141a6d6",
      "data": [
        {
          "text": "delete all details in event"
        }
      ],
      "isTemplate": false,
      "count": 0
    },
    {
      "id": "ac82c663-b2c1-49df-b9b7-24b910f779a6",
      "data": [
        {
          "text": "take out event from calendar"
        }
      ],
      "isTemplate": false,
      "count": 0
    },
    {
      "id": "cb40ade5-6efd-4973-ad56-661f3bebd0c2",
      "data": [
        {
          "text": "delete my calendar"
        }
      ],
      "isTemplate": false,
      "count": 0
    },
    {
      "id": "2bb802e2-2717-4fab-836c-def2a86c66d2",
      "data": [
        {
          "text": "change the plan of "
        },
        {
          "text": "meeting",
          "alias": "event_name",
          "meta": "@event_name",
          "userDefined": true
        }
      ],
      "isTemplate": false,
      "count": 0
    },
    {
      "id": "00010b9f-6741-4526-b69c-7a4f7f6ac012",
      "data": [
        {
          "text": "delete all "
        },
        {
          "text": "appointments",
          "alias": "event_name",
          "meta": "@event_name",
          "userDefined": true
        },
        {
          "text": " for "
        },
        {
          "text": "tomorrow",
          "alias": "date",
          "meta": "@date",
          "userDefined": true
        }
      ],
      "isTemplate": false,
      "count": 0
    },
    {
      "id": "9828ff41-8457-4c8d-a929-ce9c055d8c58",
      "data": [
        {
          "text": "erase my "
        },
        {
          "text": "appointment",
          "alias": "event_name",
          "meta": "@event_name",
          "userDefined": true
        },
        {
          "text": " for "
        },
        {
          "text": "march seven",
          "alias": "date",
          "meta": "@date",
          "userDefined": true
        }
      ],
      "isTemplate": false,
      "count": 0
    },
    {
      "id": "4e9ecdd9-c6e3-4ed4-ad67-8a7a48655c40",
      "data": [
        {
          "text": "remove "
        },
        {
          "text": "birthday party",
          "alias": "event_name",
          "meta": "@event_name",
          "userDefined": true
        }
      ],
      "isTemplate": false,
      "count": 0
    },
    {
      "id": "fb7a00b2-9a95-49f5-b727-43f26348e3f2",
      "data": [
        {
          "text": "find my next event and delete it please"
        }
      ],
      "isTemplate": false,
      "count": 0
    },
    {
      "id": "9d127e21-fbd8-4f88-b27e-cf4c2ec17cbc",
      "data": [
        {
          "text": "cancel my "
        },
        {
          "text": "birthday party",
          "alias": "event_name",
          "meta": "@event_name",
          "userDefined": true
        }
      ],
      "isTemplate": false,
      "count": 0
    },
    {
      "id": "16b1195d-97d1-4b2c-a011-bc74e23ca0ff",
      "data": [
        {
          "text": "please delete all my calendar events"
        }
      ],
      "isTemplate": false,
      "count": 0
    },
    {
      "id": "a09b7067-e80e-43d7-9e43-b74cccb361d7",
      "data": [
        {
          "text": "clear off the "
        },
        {
          "text": "vet appointment",
          "alias": "event_name",
          "meta": "@event_name",
          "userDefined": true
        },
        {
          "text": " "
        },
        {
          "text": "tomorrow",
          "alias": "date",
          "meta": "@date",
          "userDefined": true
        }
      ],
      "isTemplate": false,
      "count": 0
    },
    {
      "id": "d5dc3470-ecd3-4343-98d0-0119afc35560",
      "data": [
        {
          "text": "delete an first event of "
        },
        {
          "text": "twenty third of march twenty seventeen",
          "alias": "date",
          "meta": "@date",
          "userDefined": true
        }
      ],
      "isTemplate": false,
      "count": 0
    },
    {
      "id": "0ec17b62-4f0f-42b0-b41b-f8587b369ac0",
      "data": [
        {
          "text": "delete my "
        },
        {
          "text": "dinner",
          "alias": "meal_type",
          "meta": "@meal_type",
          "userDefined": true
        },
        {
          "text": " "
        },
        {
          "text": "tomorrow",
          "alias": "date",
          "meta": "@date",
          "userDefined": true
        }
      ],
      "isTemplate": false,
      "count": 0
    },
    {
      "id": "5f424f3d-b244-4f2d-8030-eb17ae2bcbe1",
      "data": [
        {
          "text": "clean my entire calendar"
        }
      ],
      "isTemplate": false,
      "count": 0
    },
    {
      "id": "03af9de5-7d79-4e6e-853a-f786d95357f8",
      "data": [
        {
          "text": "erase all events"
        }
      ],
      "isTemplate": false,
      "count": 0
    },
    {
      "id": "78d26581-6d36-49f0-8388-c76bcead0301",
      "data": [
        {
          "text": "please delete all calendar events"
        }
      ],
      "isTemplate": false,
      "count": 0
    },
    {
      "id": "b1377cf1-260c-448d-aa28-c961482bd7d3",
      "data": [
        {
          "text": "erase my whole calendar"
        }
      ],
      "isTemplate": false,
      "count": 0
    },
    {
      "id": "d698d595-dccb-4fe4-83b2-bf5ec35ff35f",
      "data": [
        {
          "text": "remove "
        },
        {
          "text": "john",
          "alias": "person",
          "meta": "@person",
          "userDefined": true
        },
        {
          "text": "'s "
        },
        {
          "text": "birthday",
          "alias": "event_name",
          "meta": "@event_name",
          "userDefined": true
        },
        {
          "text": " from the calendar"
        }
      ],
      "isTemplate": false,
      "count": 0
    },
    {
      "id": "fb603d39-e1bb-44f5-987c-63b04698d1f1",
      "data": [
        {
          "text": "clear up my calendar"
        }
      ],
      "isTemplate": false,
      "count": 0
    },
    {
      "id": "8570c11e-7d1c-4714-afe6-2f93f36f47ab",
      "data": [
        {
          "text": "clear everything off my calendar for the "
        },
        {
          "text": "rest of the year",
          "alias": "date",
          "meta": "@date",
          "userDefined": true
        }
      ],
      "isTemplate": false,
      "count": 0
    },
    {
      "id": "f2747d68-843a-443f-ba51-bf83787d2c69",
      "data": [
        {
          "text": "can you take out "
        },
        {
          "text": "dentist appointment",
          "alias": "event_name",
          "meta": "@event_name",
          "userDefined": true
        },
        {
          "text": " from my calendar"
        }
      ],
      "isTemplate": false,
      "count": 0
    },
    {
      "id": "8a0f6219-256a-43d8-9924-d8acc75cf196",
      "data": [
        {
          "text": "please remove this event from my calendar"
        }
      ],
      "isTemplate": false,
      "count": 0
    },
    {
      "id": "c0688bf8-ffb1-4d72-968a-bf4f531022d0",
      "data": [
        {
          "text": "can you delete the not so important events"
        }
      ],
      "isTemplate": false,
      "count": 0
    },
    {
      "id": "44234cc3-88af-438d-b0f3-3c48111baa9b",
      "data": [
        {
          "text": "erase my next event"
        }
      ],
      "isTemplate": false,
      "count": 0
    },
    {
      "id": "529af864-b447-4384-9f3f-2e3ae6c99516",
      "data": [
        {
          "text": "clear my calendar for "
        },
        {
          "text": "saturday",
          "alias": "date",
          "meta": "@date",
          "userDefined": true
        }
      ],
      "isTemplate": false,
      "count": 0
    },
    {
      "id": "9e21fe6b-fe27-4619-97cd-3315dd724964",
      "data": [
        {
          "text": "is there a way to clear my calendar"
        }
      ],
      "isTemplate": false,
      "count": 0
    },
    {
      "id": "fb1143d7-a6b2-4a8a-98c2-1b3675fc880d",
      "data": [
        {
          "text": "cancel all my "
        },
        {
          "text": "appointments",
          "alias": "event_name",
          "meta": "@event_name",
          "userDefined": true
        },
        {
          "text": " after "
        },
        {
          "text": "three pm",
          "alias": "time",
          "meta": "@time",
          "userDefined": true
        },
        {
          "text": " "
        },
        {
          "text": "today",
          "alias": "date",
          "meta": "@date",
          "userDefined": true
        },
        {
          "text": " and inform me the details"
        }
      ],
      "isTemplate": false,
      "count": 0
    },
    {
      "id": "a2a17ebb-b50b-4568-8a1e-d4cf40472afc",
      "data": [
        {
          "text": "erase events"
        }
      ],
      "isTemplate": false,
      "count": 0
    },
    {
      "id": "2b733f7e-c631-4a5b-b3ae-605dc92d773e",
      "data": [
        {
          "text": "what do i have to do "
        },
        {
          "text": "today",
          "alias": "date",
          "meta": "@date",
          "userDefined": true
        }
      ],
      "isTemplate": false,
      "count": 0
    },
    {
      "id": "85bc2c3f-37b0-4f0a-b0d2-6a8b99d13bbf",
      "data": [
        {
          "text": "get rid of the first three events in my calendar"
        }
      ],
      "isTemplate": false,
      "count": 0
    },
    {
      "id": "46d414a0-acbe-40ad-9727-04f841cd2d2e",
      "data": [
        {
          "text": "please delete the "
        },
        {
          "text": "meeting",
          "alias": "event_name",
          "meta": "@event_name",
          "userDefined": true
        },
        {
          "text": " i have with "
        },
        {
          "text": "john",
          "alias": "person",
          "meta": "@person",
          "userDefined": true
        },
        {
          "text": " "
        },
        {
          "text": "tonight",
          "alias": "timeofday",
          "meta": "@timeofday",
          "userDefined": true
        }
      ],
      "isTemplate": false,
      "count": 0
    },
    {
      "id": "55fe6637-174a-4059-80b5-3443131a35a9",
      "data": [
        {
          "text": "rm rf calendar"
        }
      ],
      "isTemplate": false,
      "count": 0
    },
    {
      "id": "7d56469c-9720-4d38-9ed8-064f11164ec2",
      "data": [
        {
          "text": "delete everything on my calendar for "
        },
        {
          "text": "the next two weeks",
          "alias": "time",
          "meta": "@time",
          "userDefined": true
        }
      ],
      "isTemplate": false,
      "count": 0
    },
    {
      "id": "bab380c2-5283-47b1-aa39-d9a9a3443ad9",
      "data": [
        {
          "text": "please remove the "
        },
        {
          "text": "doctor appointment",
          "alias": "event_name",
          "meta": "@event_name",
          "userDefined": true
        },
        {
          "text": " in my calendar for "
        },
        {
          "text": "february twelfth",
          "alias": "date",
          "meta": "@date",
          "userDefined": true
        },
        {
          "text": " at "
        },
        {
          "text": "nine am",
          "alias": "time",
          "meta": "@time",
          "userDefined": true
        }
      ],
      "isTemplate": false,
      "count": 0
    },
    {
      "id": "936bac2e-0d8f-4caf-9a5a-2f06d0f88856",
      "data": [
        {
          "text": "delete my "
        },
        {
          "text": "meeting",
          "alias": "event_name",
          "meta": "@event_name",
          "userDefined": true
        },
        {
          "text": " for "
        },
        {
          "text": "tomorrow",
          "alias": "date",
          "meta": "@date",
          "userDefined": true
        }
      ],
      "isTemplate": false,
      "count": 0
    },
    {
      "id": "d9a1e9c7-2140-4e60-923d-a34c31407273",
      "data": [
        {
          "text": "remove "
        },
        {
          "text": "father's day",
          "alias": "event_name",
          "meta": "@event_name",
          "userDefined": true
        },
        {
          "text": " from calendar"
        }
      ],
      "isTemplate": false,
      "count": 0
    },
    {
      "id": "e7cb7854-7a6d-4276-85b6-ac7c58747c0d",
      "data": [
        {
          "text": "please cancel my "
        },
        {
          "text": "next hair cut",
          "alias": "event_name",
          "meta": "@event_name",
          "userDefined": true
        }
      ],
      "isTemplate": false,
      "count": 0
    },
    {
      "id": "f8080077-f8da-4ffa-95ca-650b500f9b25",
      "data": [
        {
          "text": "please empty my calendar"
        }
      ],
      "isTemplate": false,
      "count": 0
    },
    {
      "id": "d2a18872-718b-40c4-bfc3-5a8252495a2d",
      "data": [
        {
          "text": "remove events from calendar"
        }
      ],
      "isTemplate": false,
      "count": 0
    },
    {
      "id": "dc21622c-a2a7-49d1-bafa-df8bbb8d88d9",
      "data": [
        {
          "text": "delete all meetings for "
        },
        {
          "text": "tomorrow",
          "alias": "date",
          "meta": "@date",
          "userDefined": true
        }
      ],
      "isTemplate": false,
      "count": 0
    },
    {
      "id": "e9ece6eb-ba21-4455-bd40-de494ba31756",
      "data": [
        {
          "text": "erase my "
        },
        {
          "text": "appointment",
          "alias": "event_name",
          "meta": "@event_name",
          "userDefined": true
        },
        {
          "text": " with "
        },
        {
          "text": "ted",
          "alias": "person",
          "meta": "@person",
          "userDefined": true
        }
      ],
      "isTemplate": false,
      "count": 0
    },
    {
      "id": "eea45080-ea8d-499f-bb7d-fc2992cd8381",
      "data": [
        {
          "text": "please delete all "
        },
        {
          "text": "meeting",
          "alias": "event_name",
          "meta": "@event_name",
          "userDefined": true
        },
        {
          "text": " "
        },
        {
          "text": "after seven am",
          "alias": "time",
          "meta": "@time",
          "userDefined": true
        }
      ],
      "isTemplate": false,
      "count": 0
    },
    {
      "id": "3385e6ad-ea52-4805-9b83-db5f1b9bc2eb",
      "data": [
        {
          "text": "cancel "
        },
        {
          "text": "future event",
          "alias": "event_name",
          "meta": "@event_name",
          "userDefined": true
        },
        {
          "text": " from place i worked"
        }
      ],
      "isTemplate": false,
      "count": 0
    },
    {
      "id": "f8958550-cd44-474a-90cb-25552e18663e",
      "data": [
        {
          "text": "please clean my calendar"
        }
      ],
      "isTemplate": false,
      "count": 0
    },
    {
      "id": "2aede5b6-ef6b-45d7-a0d4-7648c0512ed0",
      "data": [
        {
          "text": "i am busy "
        },
        {
          "text": "tomorrow",
          "alias": "date",
          "meta": "@date",
          "userDefined": true
        },
        {
          "text": " so delete all calendar events"
        }
      ],
      "isTemplate": false,
      "count": 0
    },
    {
      "id": "87bf1696-7f37-4c2c-a7e4-e97e1bbfddb6",
      "data": [
        {
          "text": "delete from the calendar the next event"
        }
      ],
      "isTemplate": false,
      "count": 0
    },
    {
      "id": "b0b78c85-888c-41d2-ab86-756f2c5ad506",
      "data": [
        {
          "text": "delete all scheduled events"
        }
      ],
      "isTemplate": false,
      "count": 0
    },
    {
      "id": "9a4ed77b-20bc-4c6a-a91b-90a8b3866979",
      "data": [
        {
          "text": "format data from calendar"
        }
      ],
      "isTemplate": false,
      "count": 0
    },
    {
      "id": "f34155b2-9089-45d3-83fc-c94d5595ade7",
      "data": [
        {
          "text": "find "
        },
        {
          "text": "dinner",
          "alias": "meal_type",
          "meta": "@meal_type",
          "userDefined": true
        },
        {
          "text": " with "
        },
        {
          "text": "mom",
          "alias": "relation",
          "meta": "@relation",
          "userDefined": true
        },
        {
          "text": " on my calendar and delete it"
        }
      ],
      "isTemplate": false,
      "count": 0
    },
    {
      "id": "8d3d4975-5115-4eae-b624-1d32d20bcf55",
      "data": [
        {
          "text": "remove my event at "
        },
        {
          "text": "one pm",
          "alias": "time",
          "meta": "@time",
          "userDefined": true
        },
        {
          "text": " in my calendar"
        }
      ],
      "isTemplate": false,
      "count": 0
    },
    {
      "id": "c6085e85-0243-4f5d-9408-56549855b77d",
      "data": [
        {
          "text": "please "
        },
        {
          "text": "clear",
          "alias": "time",
          "meta": "@time",
          "userDefined": true
        },
        {
          "text": " my calendar"
        }
      ],
      "isTemplate": false,
      "count": 0
    },
    {
      "id": "a7aa10af-3c87-47bd-8c80-c11a8bebf04c",
      "data": [
        {
          "text": "do remove next event from the calendar"
        }
      ],
      "isTemplate": false,
      "count": 0
    },
    {
      "id": "522f5855-ee67-40c7-abc2-58f0a5b8f7d9",
      "data": [
        {
          "text": "delete all events and content from my calendar"
        }
      ],
      "isTemplate": false,
      "count": 0
    },
    {
      "id": "e7524056-b08f-4d3d-b2b3-a26f350d9616",
      "data": [
        {
          "text": "no "
        },
        {
          "text": "lunch date",
          "alias": "event_name",
          "meta": "@event_name",
          "userDefined": true
        },
        {
          "text": " "
        },
        {
          "text": "tomorrow",
          "alias": "date",
          "meta": "@date",
          "userDefined": true
        }
      ],
      "isTemplate": false,
      "count": 0
    },
    {
      "id": "d75b3c50-9a5a-40b1-b181-e8169e47f814",
      "data": [
        {
          "text": "delete my next "
        },
        {
          "text": "meeting",
          "alias": "event_name",
          "meta": "@event_name",
          "userDefined": true
        }
      ],
      "isTemplate": false,
      "count": 0
    },
    {
      "id": "0aceea7c-efec-4ec4-8bda-54e1979b0099",
      "data": [
        {
          "text": "delete the "
        },
        {
          "text": "monthly",
          "alias": "general_frequency",
          "meta": "@general_frequency",
          "userDefined": true
        },
        {
          "text": " recurring "
        },
        {
          "text": "team meeting",
          "alias": "event_name",
          "meta": "@event_name",
          "userDefined": true
        },
        {
          "text": " till "
        },
        {
          "text": "june",
          "alias": "time",
          "meta": "@time",
          "userDefined": true
        }
      ],
      "isTemplate": false,
      "count": 0
    },
    {
      "id": "04ad78eb-d7ed-4270-8387-9b52cba3e745",
      "data": [
        {
          "text": "i will no longer be joining "
        },
        {
          "text": "mom",
          "alias": "relation",
          "meta": "@relation",
          "userDefined": true
        },
        {
          "text": " for "
        },
        {
          "text": "lunch",
          "alias": "meal_type",
          "meta": "@meal_type",
          "userDefined": true
        },
        {
          "text": " "
        },
        {
          "text": "tomorrow",
          "alias": "date",
          "meta": "@date",
          "userDefined": true
        }
      ],
      "isTemplate": false,
      "count": 0
    },
    {
      "id": "df3489cc-f2dc-4a79-8de4-0bf6dfd9a6b2",
      "data": [
        {
          "text": "destroy all events"
        }
      ],
      "isTemplate": false,
      "count": 0
    },
    {
      "id": "a871ac53-f61d-4376-84eb-3c5cef6d1f60",
      "data": [
        {
          "text": "clear my next event"
        }
      ],
      "isTemplate": false,
      "count": 0
    },
    {
      "id": "a0625dfb-8860-4ce4-9f7a-8ae7b8acf4d0",
      "data": [
        {
          "text": "check the events on calendar and delete the next event"
        }
      ],
      "isTemplate": false,
      "count": 0
    },
    {
      "id": "079fce39-103d-4ec3-ab5a-9d1f613802cf",
      "data": [
        {
          "text": "clear all data from calendar"
        }
      ],
      "isTemplate": false,
      "count": 0
    },
    {
      "id": "f1fcd0bc-fd6c-4192-aa48-3b4c3077d760",
      "data": [
        {
          "text": "cancels "
        },
        {
          "text": "lunch",
          "alias": "meal_type",
          "meta": "@meal_type",
          "userDefined": true
        },
        {
          "text": " at the "
        },
        {
          "text": "restaurant",
          "alias": "business_type",
          "meta": "@business_type",
          "userDefined": true
        },
        {
          "text": " booked for "
        },
        {
          "text": "march twenty five",
          "alias": "date",
          "meta": "@date",
          "userDefined": true
        }
      ],
      "isTemplate": false,
      "count": 0
    },
    {
      "id": "36bb55f1-9de2-4024-9b2f-49851899e91f",
      "data": [
        {
          "text": "cancel "
        },
        {
          "text": "dentist appointment",
          "alias": "event_name",
          "meta": "@event_name",
          "userDefined": true
        },
        {
          "text": " for "
        },
        {
          "text": "this week",
          "alias": "date",
          "meta": "@date",
          "userDefined": true
        }
      ],
      "isTemplate": false,
      "count": 0
    },
    {
      "id": "30e31144-63ec-4042-ad13-cb37c4dcdf8e",
      "data": [
        {
          "text": "change my plan erase my next event"
        }
      ],
      "isTemplate": false,
      "count": 0
    },
    {
      "id": "97602ec3-4cbe-49e5-a6f7-fe1a10619d46",
      "data": [
        {
          "text": "cancel the plan of "
        },
        {
          "text": "party",
          "alias": "event_name",
          "meta": "@event_name",
          "userDefined": true
        }
      ],
      "isTemplate": false,
      "count": 0
    },
    {
      "id": "d3188952-26db-4aed-9d15-d560f849edb5",
      "data": [
        {
          "text": "reset all events in calendar"
        }
      ],
      "isTemplate": false,
      "count": 0
    },
    {
      "id": "f8de4af8-a8f7-4c77-be3c-87c0e9216231",
      "data": [
        {
          "text": "erase all content in my calendar"
        }
      ],
      "isTemplate": false,
      "count": 0
    },
    {
      "id": "e1d6e2d3-0635-4c5a-b340-d5b1e5b8b4ff",
      "data": [
        {
          "text": "this event needs to be deleted"
        }
      ],
      "isTemplate": false,
      "count": 0
    },
    {
      "id": "30daa494-db2d-4b0f-8671-1d8481483de5",
      "data": [
        {
          "text": "erase my "
        },
        {
          "text": "appointment",
          "alias": "event_name",
          "meta": "@event_name",
          "userDefined": true
        },
        {
          "text": " on the "
        },
        {
          "text": "twelfth",
          "alias": "date",
          "meta": "@date",
          "userDefined": true
        },
        {
          "text": " from my calendar"
        }
      ],
      "isTemplate": false,
      "count": 0
    },
    {
      "id": "5a4f7d73-a812-4561-9e03-5a9ba82f806b",
      "data": [
        {
          "text": "remove "
        },
        {
          "text": "twenty fourth march",
          "alias": "date",
          "meta": "@date",
          "userDefined": true
        },
        {
          "text": " "
        },
        {
          "text": "meeting",
          "alias": "event_name",
          "meta": "@event_name",
          "userDefined": true
        },
        {
          "text": " from schedule"
        }
      ],
      "isTemplate": false,
      "count": 0
    },
    {
      "id": "6717f24c-918b-4566-ae7c-4e10c9b41833",
      "data": [
        {
          "text": "i want all my events deleted"
        }
      ],
      "isTemplate": false,
      "count": 0
    },
    {
      "id": "32d091ac-b2b9-4c80-8cdd-dbe52cf56fd2",
      "data": [
        {
          "text": "can you empty my calendar"
        }
      ],
      "isTemplate": false,
      "count": 0
    },
    {
      "id": "c2186185-4f86-49d8-a9a3-7b5d07f962e4",
      "data": [
        {
          "text": "delete all of my "
        },
        {
          "text": "appointments",
          "alias": "event_name",
          "meta": "@event_name",
          "userDefined": true
        },
        {
          "text": " with "
        },
        {
          "text": "dr smith",
          "alias": "person",
          "meta": "@person",
          "userDefined": true
        },
        {
          "text": " "
        },
        {
          "text": "this week",
          "alias": "date",
          "meta": "@date",
          "userDefined": true
        }
      ],
      "isTemplate": false,
      "count": 0
    },
    {
      "id": "ba43a0d1-d5c2-4703-959a-4cfa8d291d54",
      "data": [
        {
          "text": "please remove "
        },
        {
          "text": "dinner",
          "alias": "meal_type",
          "meta": "@meal_type",
          "userDefined": true
        },
        {
          "text": " date scheduled for this "
        },
        {
          "text": "friday",
          "alias": "date",
          "meta": "@date",
          "userDefined": true
        },
        {
          "text": " at "
        },
        {
          "text": "nine pm",
          "alias": "time",
          "meta": "@time",
          "userDefined": true
        }
      ],
      "isTemplate": false,
      "count": 0
    },
    {
      "id": "00b6f1a0-221b-48e9-b055-bdfb4ba89ae9",
      "data": [
        {
          "text": "delete my "
        },
        {
          "text": "appointment",
          "alias": "event_name",
          "meta": "@event_name",
          "userDefined": true
        },
        {
          "text": " "
        },
        {
          "text": "tomorrow",
          "alias": "date",
          "meta": "@date",
          "userDefined": true
        }
      ],
      "isTemplate": false,
      "count": 0
    },
    {
      "id": "61b51cc5-e5ec-4a3c-8de1-74a3669b3b2a",
      "data": [
        {
          "text": "remove "
        },
        {
          "text": "dinner",
          "alias": "meal_type",
          "meta": "@meal_type",
          "userDefined": true
        },
        {
          "text": " with "
        },
        {
          "text": "mike",
          "alias": "person",
          "meta": "@person",
          "userDefined": true
        },
        {
          "text": " from my calendar"
        }
      ],
      "isTemplate": false,
      "count": 0
    },
    {
      "id": "098289bc-537a-42ca-868f-f25155076edb",
      "data": [
        {
          "text": "delete my "
        },
        {
          "text": "dr k appointment",
          "alias": "event_name",
          "meta": "@event_name",
          "userDefined": true
        },
        {
          "text": " in "
        },
        {
          "text": "march",
          "alias": "date",
          "meta": "@date",
          "userDefined": true
        }
      ],
      "isTemplate": false,
      "count": 0
    },
    {
      "id": "a589f2fb-df47-4fd3-97d3-c21b60d9c5bc",
      "data": [
        {
          "text": "please erase the next "
        },
        {
          "text": "birthday",
          "alias": "event_name",
          "meta": "@event_name",
          "userDefined": true
        },
        {
          "text": " event"
        }
      ],
      "isTemplate": false,
      "count": 0
    },
    {
      "id": "4151cc07-ed0f-41af-9356-87d3f068447b",
      "data": [
        {
          "text": "make my calendar empty"
        }
      ],
      "isTemplate": false,
      "count": 0
    },
    {
      "id": "6f3a7e86-d2fd-4934-9648-207b5d4eb2eb",
      "data": [
        {
          "text": "cancel "
        },
        {
          "text": "sam",
          "alias": "person",
          "meta": "@person",
          "userDefined": true
        },
        {
          "text": "'s "
        },
        {
          "text": "party",
          "alias": "event_name",
          "meta": "@event_name",
          "userDefined": true
        }
      ],
      "isTemplate": false,
      "count": 0
    },
    {
      "id": "ff64303f-318d-4268-8bcd-8d95d62b33ef",
      "data": [
        {
          "text": "please delete this event"
        }
      ],
      "isTemplate": false,
      "count": 0
    },
    {
      "id": "3a0d381f-cccb-4daa-8939-96175413afad",
      "data": [
        {
          "text": "delete all events in calendar"
        }
      ],
      "isTemplate": false,
      "count": 0
    },
    {
      "id": "87a732f5-3d36-447e-86de-5c0eb7965077",
      "data": [
        {
          "text": "i am no longer attending the "
        },
        {
          "text": "wedding",
          "alias": "event_name",
          "meta": "@event_name",
          "userDefined": true
        },
        {
          "text": " on the "
        },
        {
          "text": "tenth",
          "alias": "date",
          "meta": "@date",
          "userDefined": true
        },
        {
          "text": " so remove it from my calendar"
        }
      ],
      "isTemplate": false,
      "count": 0
    },
    {
      "id": "e499316b-c044-4d51-9412-6f63fb384c9c",
      "data": [
        {
          "text": "delete every event"
        }
      ],
      "isTemplate": false,
      "count": 0
    },
    {
      "id": "e8a713e8-4357-4bfd-bba5-40065d0858f7",
      "data": [
        {
          "text": "delete the scheduled "
        },
        {
          "text": "meeting",
          "alias": "event_name",
          "meta": "@event_name",
          "userDefined": true
        },
        {
          "text": " on "
        },
        {
          "text": "fourth october",
          "alias": "date",
          "meta": "@date",
          "userDefined": true
        },
        {
          "text": " "
        },
        {
          "text": "twelve pm",
          "alias": "time",
          "meta": "@time",
          "userDefined": true
        }
      ],
      "isTemplate": false,
      "count": 0
    },
    {
      "id": "ea0ebd69-0e83-4dbd-95f7-cc64f6877420",
      "data": [
        {
          "text": "open calendar and erase all events for "
        },
        {
          "text": "all months",
          "alias": "time",
          "meta": "@time",
          "userDefined": true
        }
      ],
      "isTemplate": false,
      "count": 0
    }
  ],
  "id": "360e38da-f5f8-43c6-b576-d0ff586ba820",
  "name": "calendar_remove",
  "auto": true,
  "contexts": [],
  "responses": [
    {
      "resetContexts": false,
      "affectedContexts": [],
      "parameters": [
        {
          "dataType": "@app_name",
          "name": "app_name",
          "value": "$app_name"
        },
        {
          "dataType": "@business_type",
          "name": "business_type",
          "value": "$business_type"
        },
        {
          "dataType": "@date",
          "name": "date",
          "value": "$date"
        },
        {
          "dataType": "@event_name",
          "name": "event_name",
          "value": "$event_name"
        },
        {
          "dataType": "@general_frequency",
          "name": "general_frequency",
          "value": "$general_frequency"
        },
        {
          "dataType": "@meal_type",
          "name": "meal_type",
          "value": "$meal_type"
        },
        {
          "dataType": "@person",
          "name": "person",
          "value": "$person"
        },
        {
          "dataType": "@place_name",
          "name": "place_name",
          "value": "$place_name"
        },
        {
          "dataType": "@relation",
          "name": "relation",
          "value": "$relation"
        },
        {
          "dataType": "@time",
          "name": "time",
          "value": "$time"
        },
        {
          "dataType": "@timeofday",
          "name": "timeofday",
          "value": "$timeofday"
        }
      ],
      "messages": [
        {
          "type": 0,
          "speech": []
        }
      ]
    }
  ],
  "webhookUsed": false,
  "webhookForSlotFilling": false,
  "fallbackIntent": false,
  "events": []
}
